README.md
setup.py
vt/__init__.py
vt/__main__.py
vt/vt.py
vt.egg-info/PKG-INFO
vt.egg-info/SOURCES.txt
vt.egg-info/dependency_links.txt
vt.egg-info/entry_points.txt
vt.egg-info/requires.txt
vt.egg-info/top_level.txt
vt/thirdpart/__init__.py
vt/thirdpart/outlook_parser.py