Metadata-Version: 1.1
Name: vt
Version: 3.1.3.4
Summary: VirusTotal Full API
Home-page: https://github.com/doomedraven/VirusTotalApi
Author: Andriy Brukhovetskyy - doomedraven
Author-email: UNKNOWN
License: For fun :)
Keywords: virustotal vt automated malware analysis threat intelligence cert soc
Platform: UNKNOWN
Classifier: Development Status :: 5 - Production/Stable
Classifier: Environment :: Console
Classifier: Intended Audience :: Information Technology
Classifier: Intended Audience :: Science/Research
Classifier: Natural Language :: English
Classifier: Operating System :: POSIX :: Linux
Classifier: Programming Language :: Python :: 2.7
Classifier: Programming Language :: Python :: 3.5
Classifier: Programming Language :: Python :: 3.6
Classifier: Topic :: Security
